_time_machine.cpython-314t-x86_64-linux-musl.so
time_machine/__init__.py
time_machine/__main__.py
time_machine/cli.py
time_machine/py.typed
time_machine-3.2.0.dist-info/METADATA
time_machine-3.2.0.dist-info/WHEEL
time_machine-3.2.0.dist-info/entry_points.txt
time_machine-3.2.0.dist-info/top_level.txt
time_machine-3.2.0.dist-info/RECORD
time_machine-3.2.0.dist-info/licenses/LICENSE
