Metadata-Version: 2.4
Name: time-machine
Version: 3.2.0
Summary: Travel through time in your tests.
Author-email: Adam Johnson <me@adamj.eu>
License-Expression: MIT
Project-URL: Changelog, https://time-machine.readthedocs.io/en/latest/changelog.html
Project-URL: Documentation, https://time-machine.readthedocs.io/
Project-URL: Funding, https://adamj.eu/books/
Project-URL: Repository, https://github.com/adamchainz/time-machine
Keywords: date,datetime,mock,test,testing,tests,time,warp
Classifier: Development Status :: 5 - Production/Stable
Classifier: Framework :: Pytest
Classifier: Intended Audience :: Developers
Classifier: Natural Language :: English
Classifier: Operating System :: OS Independent
Classifier: Programming Language :: Python :: 3 :: Only
Classifier: Programming Language :: Python :: 3.10
Classifier: Programming Language :: Python :: 3.11
Classifier: Programming Language :: Python :: 3.12
Classifier: Programming Language :: Python :: 3.13
Classifier: Programming Language :: Python :: 3.14
Classifier: Typing :: Typed
Requires-Python: >=3.10
License-File: LICENSE
Provides-Extra: cli
Requires-Dist: tokenize-rt; extra == "cli"
Provides-Extra: dateutil
Requires-Dist: python-dateutil>=2.8.2; extra == "dateutil"
Dynamic: license-file
